convertion/__init__.py
convertion/badwords.py
convertion/convertion.py
convertion/dictionary.txt
convertion/frequency.py
convertion/spacing_checker.py
convertion/spell_checker.py
convertion/spell_checker_run.py
word_processing_tot-0.0.2.dist-info/METADATA
word_processing_tot-0.0.2.dist-info/WHEEL
word_processing_tot-0.0.2.dist-info/RECORD
