Metadata-Version: 2.4
Name: Word-Processing-tot
Version: 0.0.2
Summary: A library for word processing
Project-URL: Homepage, https://github.com/hlpearm1515/forlibrary
Project-URL: Issues, https://github.com/hlpearm1515/forlibrary/issues
Author-email: man <redboy1215@gmail.com>
Classifier: License :: OSI Approved :: MIT License
Classifier: Operating System :: OS Independent
Classifier: Programming Language :: Python :: 3
Requires-Python: >=3.8
